{  "name": "MedBoard AI Tutor",  "description": "MedBoard AI Tutor is an intelligent, interactive chatbot designed to help medical students prepare for their board examinations by engaging with clinical questions and providing personalized feedback. It offers a dynamic learning experience with robust performance tracking and flexible authentication options.",  "technologies": [    "AI",    "Cloud Computing",    "Containerization",    "Multi-Provider Authentication",    "Analytics Dashboard"  ],  "category": "web-app",  "status": "active",  "language": "JavaScript"}
